pyBrematic/__init__.py
pyBrematic/action.py
pyBrematic/version.py
pyBrematic/devices/__init__.py
pyBrematic/devices/autopairdevice.py
pyBrematic/devices/device.py
pyBrematic/devices/brennenstuhl/RCR1000N.py
pyBrematic/devices/brennenstuhl/RCS1000N.py
pyBrematic/devices/brennenstuhl/__init__.py
pyBrematic/devices/brennenstuhl/tests/__init__.py
pyBrematic/devices/brennenstuhl/tests/brennenstuhl_test.py
pyBrematic/devices/elro/AB440SA.py
pyBrematic/devices/elro/__init__.py
pyBrematic/devices/elro/tests/__init__.py
pyBrematic/devices/elro/tests/elro_test.py
pyBrematic/devices/intertechno/CMR1000.py
pyBrematic/devices/intertechno/CMR300.py
pyBrematic/devices/intertechno/CMR500.py
pyBrematic/devices/intertechno/ITL500.py
pyBrematic/devices/intertechno/ITR300.py
pyBrematic/devices/intertechno/ITR3500.py
pyBrematic/devices/intertechno/PAR1500.py
pyBrematic/devices/intertechno/__init__.py
pyBrematic/devices/intertechno/intertechnodevice.py
pyBrematic/devices/intertechno/tools.py
pyBrematic/devices/intertechno/tests/ITL500_test.py
pyBrematic/devices/intertechno/tests/__init__.py
pyBrematic/devices/intertechno/tests/intertechno_test.py
pyBrematic/devices/intertechno/tests/intertechnodevice_test.py
pyBrematic/devices/intertechno/tests/tools_test.py
pyBrematic/devices/tests/__init__.py
pyBrematic/devices/tests/autopairdevice_test.py
pyBrematic/devices/tests/device_test.py
pyBrematic/exceptions/GatewayNotSupportedException.py
pyBrematic/exceptions/__init__.py
pyBrematic/gateways/__init__.py
pyBrematic/gateways/brennenstuhl_gateway.py
pyBrematic/gateways/connair_gateway.py
pyBrematic/gateways/gateway.py
pyBrematic/gateways/intertechno_gateway.py
pyBrematic/gateways/tests/__init__.py
pyBrematic/gateways/tests/brennenstuhl_gateway_test.py
pyBrematic/gateways/tests/connair_gateway_test.py
pyBrematic/gateways/tests/intertechno_gateway_test.py
pyBrematic/utils/__init__.py
pyBrematic/utils/encoding.py
pyBrematic/utils/rand.py
pyBrematic/utils/singleton.py
pyBrematic/utils/storage.py
pyBrematic-1.2.1.dist-info/LICENSE
pyBrematic-1.2.1.dist-info/METADATA
pyBrematic-1.2.1.dist-info/WHEEL
pyBrematic-1.2.1.dist-info/top_level.txt
pyBrematic-1.2.1.dist-info/RECORD
