Metadata-Version: 2.1
Name: pyBrematic
Version: 1.2.1
Summary: Python code for controlling Brematic remote power outlets and potentially other stuff
Home-page: https://github.com/d-Rickyy-b/pyBrematic
Author: d-Rickyy-b
Author-email: pyBrematic@rico-j.de
License: MIT
Keywords: python telegram bot api wrapper
Platform: UNKNOWN
Classifier: Development Status :: 5 - Production/Stable
Classifier: Environment :: Console
Classifier: Intended Audience :: Developers
Classifier: Intended Audience :: Science/Research
Classifier: License :: OSI Approved :: MIT License
Classifier: Operating System :: OS Independent
Classifier: Topic :: Software Development :: Libraries :: Python Modules
Classifier: Topic :: Internet
Classifier: Programming Language :: Python
Classifier: Programming Language :: Python :: 3.5
Classifier: Programming Language :: Python :: 3.6
Classifier: Programming Language :: Python :: 3.7
